[
    {
        "key": "dbln",
        "value": "%7B%22100076387592229%22%3A%22srXqwN0p%22%2C%2261580158126952%22%3A%22t3AJTMX1%22%7D",
        "domain": "facebook.com",
        "path": "/login/device-based/",
        "hostOnly": false,
        "creation": "2026-02-07T07:03:08.657Z",
        "lastAccessed": "2026-02-07T07:03:08.658Z"
    },
    {
        "key": "datr",
        "value": "1S9XaeJ0cFAAttQXtH2ugN8e",
        "domain": "facebook.com",
        "path": "/",
        "hostOnly": false,
        "creation": "2026-02-07T07:03:08.658Z",
        "lastAccessed": "2026-02-07T07:03:08.658Z"
    },
    {
        "key": "sb",
        "value": "1S9XaTn8ByvSnWo-wJeYOIrE",
        "domain": "facebook.com",
        "path": "/",
        "hostOnly": false,
        "creation": "2026-02-07T07:03:08.658Z",
        "lastAccessed": "2026-02-07T07:03:08.658Z"
    },
    {
        "key": "vpd",
        "value": "v1%3B852x432x2.125537157058716",
        "domain": "facebook.com",
        "path": "/",
        "hostOnly": false,
        "creation": "2026-02-07T07:03:08.658Z",
        "lastAccessed": "2026-02-07T07:03:08.658Z"
    },
    {
        "key": "ps_l",
        "value": "1",
        "domain": "facebook.com",
        "path": "/",
        "hostOnly": false,
        "creation": "2026-02-07T07:03:08.658Z",
        "lastAccessed": "2026-02-07T07:03:08.658Z"
    },
    {
        "key": "ps_n",
        "value": "1",
        "domain": "facebook.com",
        "path": "/",
        "hostOnly": false,
        "creation": "2026-02-07T07:03:08.658Z",
        "lastAccessed": "2026-02-07T07:03:08.658Z"
    },
    {
        "key": "pas",
        "value": "61580158126952%3ADcG4swAgxr%2C61585518012262%3Awa2YOrU8Sb%2C61585923549498%3AYXHHsf32Te%2C61581198121424%3Ax0p04u48hf%2C100076387592229%3AO410I06KU8%2C61587073715148%3AgAbEMmT6Dv",
        "domain": "facebook.com",
        "path": "/",
        "hostOnly": false,
        "creation": "2026-02-07T07:03:08.658Z",
        "lastAccessed": "2026-02-07T07:03:08.658Z"
    },
    {
        "key": "locale",
        "value": "en_GB",
        "domain": "facebook.com",
        "path": "/",
        "hostOnly": false,
        "creation": "2026-02-07T07:03:08.658Z",
        "lastAccessed": "2026-02-07T07:03:08.658Z"
    },
    {
        "key": "dpr",
        "value": "2.3369150161743164",
        "domain": "facebook.com",
        "path": "/",
        "hostOnly": false,
        "creation": "2026-02-07T07:03:08.658Z",
        "lastAccessed": "2026-02-07T07:03:08.658Z"
    },
    {
        "key": "wl_cbv",
        "value": "v2%3Bclient_version%3A3074%3Btimestamp%3A1770015698",
        "domain": "facebook.com",
        "path": "/",
        "hostOnly": false,
        "creation": "2026-02-07T07:03:08.658Z",
        "lastAccessed": "2026-02-07T07:03:08.658Z"
    },
    {
        "key": "c_user",
        "value": "61585567957824",
        "domain": "facebook.com",
        "path": "/",
        "hostOnly": false,
        "creation": "2026-02-07T07:03:08.658Z",
        "lastAccessed": "2026-02-07T07:03:08.658Z"
    },
    {
        "key": "wd",
        "value": "1049x2067",
        "domain": "facebook.com",
        "path": "/",
        "hostOnly": false,
        "creation": "2026-02-07T07:03:08.658Z",
        "lastAccessed": "2026-02-07T07:03:08.658Z"
    },
    {
        "key": "fr",
        "value": "1J4tXDvLf9Wz91ivx.AWeZTQ63Ye3H4JqYa52a4Oguf7Z7JfK1f8LpBaQ9381H_N8pPww.BphuLt..AAA.0.0.BphuLt.AWcZV4uMGrFMSTu_YawIC19PjdY",
        "domain": "facebook.com",
        "path": "/",
        "hostOnly": false,
        "creation": "2026-02-07T07:03:08.658Z",
        "lastAccessed": "2026-02-07T07:03:08.658Z"
    },
    {
        "key": "xs",
        "value": "49%3ADqEJJmDFw1DSAQ%3A2%3A1770447420%3A-1%3A-1%3A%3AAcyLukU-Suy_IW6qzP2OJKvl6idh5jtfmaqpcJiJng",
        "domain": "facebook.com",
        "path": "/",
        "hostOnly": false,
        "creation": "2026-02-07T07:03:08.658Z",
        "lastAccessed": "2026-02-07T07:03:08.658Z"
    },
    {
        "key": "presence",
        "value": "C%7B%22lm3%22%3A%22g.1238851018311281%22%2C%22t3%22%3A%5B%5D%2C%22utc3%22%3A1770447656909%2C%22v%22%3A1%7D",
        "domain": "facebook.com",
        "path": "/",
        "hostOnly": false,
        "creation": "2026-02-07T07:03:08.658Z",
        "lastAccessed": "2026-02-07T07:03:08.658Z"
    }
]
